pygame_spiel/__init__.py
pygame_spiel/main.py
pygame_spiel/menu.py
pygame_spiel/utils.py
pygame_spiel/bots/__init__.py
pygame_spiel/bots/dqn.py
pygame_spiel/bots/dqn_pytorch.py
pygame_spiel/bots/dummy.py
pygame_spiel/games/__init__.py
pygame_spiel/games/base.py
pygame_spiel/games/breakthrough.py
pygame_spiel/games/factory.py
pygame_spiel/games/settings.py
pygame_spiel/games/tic_tac_toe.py
pygame_spiel/images/.DS_Store
pygame_spiel/images/breakthrough/chess_board.png
pygame_spiel/images/breakthrough/pawn_black.png
pygame_spiel/images/breakthrough/pawn_white.png
pygame_spiel/images/breakthrough/pawn_white_selected.png
pygame_spiel/images/tic_tac_toe/x_image.png
pygame_spiel-1.0.0.dist-info/LICENSE
pygame_spiel-1.0.0.dist-info/METADATA
pygame_spiel-1.0.0.dist-info/WHEEL
pygame_spiel-1.0.0.dist-info/entry_points.txt
pygame_spiel-1.0.0.dist-info/top_level.txt
pygame_spiel-1.0.0.dist-info/RECORD
