Metadata-Version: 2.1
Name: pygame_spiel
Version: 1.0.0
Summary: Pygame spiel
Author-email: Giovanni Ortolani <giovorto@pm.me>
Maintainer-email: Giovanni Ortolani <giovorto@pm.me>
License: MIT License
Project-URL: Homepage, https://github.com/giogix2/pygame_spiel
Project-URL: Repository, https://github.com/giogix2/pygame_spiel
Keywords: open_spiel,pygame
Classifier: Programming Language :: Python :: 3
Classifier: License :: OSI Approved :: MIT License
Classifier: Operating System :: OS Independent
Requires-Python: >=3.9.1
License-File: LICENSE
Requires-Dist: pygame ==2.5.0
Requires-Dist: tensorflow ==2.13.0
Requires-Dist: gdown ==4.7.1
Requires-Dist: pygame-menu ==4.4.3
Provides-Extra: spiel
Requires-Dist: open-spiel ==1.3 ; extra == 'spiel'
